rpi_remote/__init__.py
rpi_remote/forward.py
rpi_remote/rpi_remote.py
rpi_remote-2.1.1.dist-info/LICENSE
rpi_remote-2.1.1.dist-info/METADATA
rpi_remote-2.1.1.dist-info/WHEEL
rpi_remote-2.1.1.dist-info/entry_points.txt
rpi_remote-2.1.1.dist-info/top_level.txt
rpi_remote-2.1.1.dist-info/RECORD
