Metadata-Version: 2.1
Name: rpi-remote
Version: 2.1.1
Summary: Rpi remote client
Author-email: Aron Radics <radics.aron.jozsef@gmail.com>
Project-URL: Homepage, https://github.com/radaron/rpi_remote_client
Classifier: Programming Language :: Python :: 3
Classifier: License :: OSI Approved :: MIT License
Classifier: Operating System :: OS Independent
Requires-Python: >=3.9
License-File: LICENSE
Requires-Dist: requests >=2.28.1
Requires-Dist: psutil >=5.8.0
Provides-Extra: dev
Requires-Dist: build ; extra == 'dev'
Requires-Dist: twine ; extra == 'dev'
Requires-Dist: pylint ; extra == 'dev'
